{
  "forge_marker": 1,
  "parent": "block/cube_all",
  "variants": {
    "variant=gold": {
      "textures": {
        "all": "oceanheartr:strange_ore_gold"
      }
    },
    "variant=leve_soul": {
      "textures": {
        "all": "oceanheartr:strange_ore_leve_soul"
      }
    },
    "variant=ocean_soul": {
      "textures": {
        "all": "oceanheartr:strange_ore_ocean_soul"
      }
    },
    "variant=end": {
      "textures": {
        "all": "oceanheartr:strange_ore_end"
      }
    }
  }
}